<?xml version="1.0" encoding="utf-8"?>
<LinearLayout xmlns:android="http://schemas.android.com/apk/res/android"
    xmlns:app="http://schemas.android.com/apk/res-auto"
    xmlns:tools="http://schemas.android.com/tools"
    android:layout_width="match_parent"
    android:layout_height="wrap_content"
    tools:context=".MainActivity"
    android:orientation="vertical"
    android:background="@drawable/layout">

    <ImageButton
        android:layout_width="37dp"
        android:layout_height="37dp"
        android:layout_margin="5dp"
        android:layout_marginTop="5dp"
        android:background="@drawable/back" />

    <ImageView
        android:layout_width="match_parent"
        android:layout_height="120dp"
        android:layout_marginBottom="20dp"
        android:src="@drawable/logo" />
    //
    <com.google.android.material.textfield.TextInputLayout
        android:layout_width="match_parent"
        android:layout_height="wrap_content"
        android:layout_marginBottom="20dp">

        <EditText
            android:id="@+id/edtHoTen"
            android:inputType="text"
            android:layout_width="match_parent"
            android:layout_height="match_parent"
            android:layout_marginRight="6dp"
            android:textColor="#E0E0E0"
            android:hint="Họ Và Tên">

        </EditText>
    </com.google.android.material.textfield.TextInputLayout>


    <com.google.android.material.textfield.TextInputLayout
        android:layout_width="match_parent"
        android:layout_height="wrap_content"
        android:layout_marginBottom="20dp"
        app:counterMaxLength="10">

        <EditText
            android:id="@+id/edtSdt"
            android:inputType="phone"
            android:maxLength="10"
            android:layout_width="match_parent"
            android:layout_height="wrap_content"
            android:layout_marginRight="6dp"
            android:textColor="#E0E0E0"
            android:hint="Số Điện Thoại">

        </EditText>
    </com.google.android.material.textfield.TextInputLayout>


    <com.google.android.material.textfield.TextInputLayout
        android:layout_width="match_parent"
        android:layout_height="wrap_content"
        android:layout_marginBottom="20dp">

        <EditText
            android:id="@+id/edtDiaChi"
            android:inputType="textMultiLine"
            android:lines="3"
            android:layout_width="match_parent"
            android:layout_height="wrap_content"
            android:layout_marginRight="6dp"
            android:hint="Địa Chỉ"
            android:textColor="#E0E0E0">

        </EditText>
    </com.google.android.material.textfield.TextInputLayout>


    <com.google.android.material.textfield.TextInputLayout
        android:layout_width="match_parent"
        android:layout_height="wrap_content"
        android:layout_marginBottom="20dp">

        <EditText
            android:id="@+id/edtGhiChu"
            android:inputType="textMultiLine"
            android:lines="3"
            android:layout_width="match_parent"
            android:layout_height="wrap_content"
            android:layout_marginRight="6dp"
            android:hint="Ghi Chú"
            android:textColor="#E0E0E0">

        </EditText>
    </com.google.android.material.textfield.TextInputLayout>

    <ImageButton
        android:id="@+id/btnTiepTuc"
        android:layout_width="100dp"
        android:layout_height="55dp"
        android:background="@drawable/button5"
        android:layout_marginLeft="280dp">
    </ImageButton>

</LinearLayout>